setup.py
client/__init__.py
client/add_contact_windows.py
client/chat_dialog.py
client/chat_gui_ver2.py
client/client_chat_gui_v3.py
client/client_class.py
client/client_register_from.py
client/login_dialog.py
client/metaclass.py
client/transport.py
client/common/__init__.py
client/common/external_func.py
client/common/vars.py
first_message_client_from_lev.egg-info/PKG-INFO
first_message_client_from_lev.egg-info/SOURCES.txt
first_message_client_from_lev.egg-info/dependency_links.txt
first_message_client_from_lev.egg-info/requires.txt
first_message_client_from_lev.egg-info/top_level.txt